dash_traverser_component
