Metadata-Version: 1.1
Name: dash-traverser-component
Version: 0.0.2
Summary: A dash component for visulising an MDSplus (https://www.mdsplus.org/) database
Home-page: UNKNOWN
Author: Peter Buxton <peter.buxton@tokamakenergy.co.uk>
Author-email: UNKNOWN
License: UNKNOWN
Platform: UNKNOWN
Classifier: Framework :: Dash
